bstadlbauer/flytekitplugins/dask/__init__.py
bstadlbauer/flytekitplugins/dask/config.py
bstadlbauer/flytekitplugins/dask/constants.py
bstadlbauer/flytekitplugins/dask/errors.py
bstadlbauer/flytekitplugins/dask/task.py
bstadlbauer.flytekitplugins_dask-0.0.0.dist-info/LICENSE
bstadlbauer.flytekitplugins_dask-0.0.0.dist-info/WHEEL
bstadlbauer.flytekitplugins_dask-0.0.0.dist-info/METADATA
bstadlbauer.flytekitplugins_dask-0.0.0.dist-info/RECORD
